README.md
setup.py
airsim_gym/__init__.py
airsim_gym.egg-info/PKG-INFO
airsim_gym.egg-info/SOURCES.txt
airsim_gym.egg-info/dependency_links.txt
airsim_gym.egg-info/requires.txt
airsim_gym.egg-info/top_level.txt
airsim_gym/envs/AirSimGymMultirotor.py
airsim_gym/envs/AirSimMultirotorClient.py
airsim_gym/envs/__init__.py