Metadata-Version: 1.1
Name: airsim-gym
Version: 0.1.0
Summary: An OpenAI Gym environment for Microsoft's AirSim Multirotor simulator
Home-page: https://github.com/Kamaropoulos/AirSim_Gym
Author: Konstantinos Kamaropoulos
Author-email: k@kamaropoulos.com
License: MIT
Download-URL: https://github.com/Kamaropoulos/AirSim_Gym/archive/0.1.0.tar.gz
Keywords: AirSim,OpenAI Gym,Gym,reinforcement learning,multirotor
Platform: UNKNOWN
